{
  "aban": "abandon",
  "abil": "ability",
  "able": "able",
  "abou": "about",
  "abov": "above",
  "abse": "absent",
  "abso": "absorb",
  "abst": "abstract",
  "absu": "absurd",
  "abus": "abuse",
  "acce": "access",
  "acci": "accident",
  "acco": "account",
  "accu": "accuse",
  "achi": "achieve",
  "acid": "acid",
  "acou": "acoustic",
  "acqu": "acquire",
  "acro": "across",
  "act-": "act",
  "acti": "action",
  "acto": "actor",
  "actr": "actress",
  "actu": "actual",
  "adap": "adapt",
  "add-": "add",
  "addi": "addict",
  "addr": "address",
  "adju": "adjust",
  "admi": "admit",
  "adul": "adult",
  "adva": "advance",
  "advi": "advice",
  "aero": "aerobic",
  "affa": "affair",
  "affo": "afford",
  "afra": "afraid",
  "agai": "again",
  "age-": "age",
  "agen": "agent",
  "agre": "agree",
  "ahea": "ahead",
  "aim-": "aim",
  "air-": "air",
  "airp": "airport",
  "aisl": "aisle",
  "alar": "alarm",
  "albu": "album",
  "alco": "alcohol",
  "aler": "alert",
  "alie": "alien",
  "all-": "all",
  "alle": "alley",
  "allo": "allow",
  "almo": "almost",
  "alon": "alone",
  "alph": "alpha",
  "alre": "already",
  "also": "also",
  "alte": "alter",
  "alwa": "always",
  "amat": "amateur",
  "amaz": "amazing",
  "amon": "among",
  "amou": "amount",
  "amus": "amused",
  "anal": "analyst",
  "anch": "anchor",
  "anci": "ancient",
  "ange": "anger",
  "angl": "angle",
  "angr": "angry",
  "anim": "animal",
  "ankl": "ankle",
  "anno": "announce",
  "annu": "annual",
  "anot": "another",
  "answ": "answer",
  "ante": "antenna",
  "anti": "antique",
  "anxi": "anxiety",
  "any-": "any",
  "apar": "apart",
  "apol": "apology",
  "appe": "appear",
  "appl": "apple",
  "appr": "approve",
  "apri": "april",
  "arch": "arch",
  "arct": "arctic",
  "area": "area",
  "aren": "arena",
  "argu": "argue",
  "arm-": "arm",
  "arme": "armed",
  "armo": "armor",
  "army": "army",
  "arou": "around",
  "arra": "arrange",
  "arre": "arrest",
  "arri": "arrive",
  "arro": "arrow",
  "art-": "art",
  "arte": "artefact",
  "arti": "artist",
  "artw": "artwork",
  "ask-": "ask",
  "aspe": "aspect",
  "assa": "assault",
  "asse": "asset",
  "assi": "assist",
  "assu": "assume",
  "asth": "asthma",
  "athl": "athlete",
  "atom": "atom",
  "atta": "attack",
  "atte": "attend",
  "atti": "attitude",
  "attr": "attract",
  "auct": "auction",
  "audi": "audit",
  "augu": "august",
  "aunt": "aunt",
  "auth": "author",
  "auto": "auto",
  "autu": "autumn",
  "aver": "average",
  "avoc": "avocado",
  "avoi": "avoid",
  "awak": "awake",
  "awar": "aware",
  "away": "away",
  "awes": "awesome",
  "awfu": "awful",
  "awkw": "awkward",
  "axis": "axis",
  "baby": "baby",
  "bach": "bachelor",
  "baco": "bacon",
  "badg": "badge",
  "bag-": "bag",
  "bala": "balance",
  "balc": "balcony",
  "ball": "ball",
  "bamb": "bamboo",
  "bana": "banana",
  "bann": "banner",
  "bar-": "bar",
  "bare": "barely",
  "barg": "bargain",
  "barr": "barrel",
  "base": "base",
  "basi": "basic",
  "bask": "basket",
  "batt": "battle",
  "beac": "beach",
  "bean": "bean",
  "beau": "beauty",
  "beca": "because",
  "beco": "become",
  "beef": "beef",
  "befo": "before",
  "begi": "begin",
  "beha": "behave",
  "behi": "behind",
  "beli": "believe",
  "belo": "below",
  "belt": "belt",
  "benc": "bench",
  "bene": "benefit",
  "best": "best",
  "betr": "betray",
  "bett": "better",
  "betw": "between",
  "beyo": "beyond",
  "bicy": "bicycle",
  "bid-": "bid",
  "bike": "bike",
  "bind": "bind",
  "biol": "biology",
  "bird": "bird",
  "birt": "birth",
  "bitt": "bitter",
  "blac": "black",
  "blad": "blade",
  "blam": "blame",
  "blan": "blanket",
  "blas": "blast",
  "blea": "bleak",
  "bles": "bless",
  "blin": "blind",
  "bloo": "blood",
  "blos": "blossom",
  "blou": "blouse",
  "blue": "blue",
  "blur": "blur",
  "blus": "blush",
  "boar": "board",
  "boat": "boat",
  "body": "body",
  "boil": "boil",
  "bomb": "bomb",
  "bone": "bone",
  "bonu": "bonus",
  "book": "book",
  "boos": "boost",
  "bord": "border",
  "bori": "boring",
  "borr": "borrow",
  "boss": "boss",
  "bott": "bottom",
  "boun": "bounce",
  "box-": "box",
  "boy-": "boy",
  "brac": "bracket",
  "brai": "brain",
  "bran": "brand",
  "bras": "brass",
  "brav": "brave",
  "brea": "bread",
  "bree": "breeze",
  "bric": "brick",
  "brid": "bridge",
  "brie": "brief",
  "brig": "bright",
  "brin": "bring",
  "bris": "brisk",
  "broc": "broccoli",
  "brok": "broken",
  "bron": "bronze",
  "broo": "broom",
  "brot": "brother",
  "brow": "brown",
  "brus": "brush",
  "bubb": "bubble",
  "budd": "buddy",
  "budg": "budget",
  "buff": "buffalo",
  "buil": "build",
  "bulb": "bulb",
  "bulk": "bulk",
  "bull": "bullet",
  "bund": "bundle",
  "bunk": "bunker",
  "burd": "burden",
  "burg": "burger",
  "burs": "burst",
  "bus-": "bus",
  "busi": "business",
  "busy": "busy",
  "butt": "butter",
  "buye": "buyer",
  "buzz": "buzz",
  "cabb": "cabbage",
  "cabi": "cabin",
  "cabl": "cable",
  "cact": "cactus",
  "cage": "cage",
  "cake": "cake",
  "call": "call",
  "calm": "calm",
  "came": "camera",
  "camp": "camp",
  "can-": "can",
  "cana": "canal",
  "canc": "cancel",
  "cand": "candy",
  "cann": "cannon",
  "cano": "canoe",
  "canv": "canvas",
  "cany": "canyon",
  "capa": "capable",
  "capi": "capital",
  "capt": "captain",
  "car-": "car",
  "carb": "carbon",
  "card": "card",
  "carg": "cargo",
  "carp": "carpet",
  "carr": "carry",
  "cart": "cart",
  "case": "case",
  "cash": "cash",
  "casi": "casino",
  "cast": "castle",
  "casu": "casual",
  "cat-": "cat",
  "cata": "catalog",
  "catc": "catch",
  "cate": "category",
  "catt": "cattle",
  "caug": "caught",
  "caus": "cause",
  "caut": "caution",
  "cave": "cave",
  "ceil": "ceiling",
  "cele": "celery",
  "ceme": "cement",
  "cens": "census",
  "cent": "century",
  "cere": "cereal",
  "cert": "certain",
  "chai": "chair",
  "chal": "chalk",
  "cham": "champion",
  "chan": "change",
  "chao": "chaos",
  "chap": "chapter",
  "char": "charge",
  "chas": "chase",
  "chat": "chat",
  "chea": "cheap",
  "chec": "check",
  "chee": "cheese",
  "chef": "chef",
  "cher": "cherry",
  "ches": "chest",
  "chic": "chicken",
  "chie": "chief",
  "chil": "child",
  "chim": "chimney",
  "choi": "choice",
  "choo": "choose",
  "chro": "chronic",
  "chuc": "chuckle",
  "chun": "chunk",
  "chur": "churn",
  "ciga": "cigar",
  "cinn": "cinnamon",
  "circ": "circle",
  "citi": "citizen",
  "city": "city",
  "civi": "civil",
  "clai": "claim",
  "clap": "clap",
  "clar": "clarify",
  "claw": "claw",
  "clay": "clay",
  "clea": "clean",
  "cler": "clerk",
  "clev": "clever",
  "clic": "click",
  "clie": "client",
  "clif": "cliff",
  "clim": "climb",
  "clin": "clinic",
  "clip": "clip",
  "cloc": "clock",
  "clog": "clog",
  "clos": "close",
  "clot": "cloth",
  "clou": "cloud",
  "clow": "clown",
  "club": "club",
  "clum": "clump",
  "clus": "cluster",
  "clut": "clutch",
  "coac": "coach",
  "coas": "coast",
  "coco": "coconut",
  "code": "code",
  "coff": "coffee",
  "coil": "coil",
  "coin": "coin",
  "coll": "collect",
  "colo": "color",
  "colu": "column",
  "comb": "combine",
  "come": "come",
  "comf": "comfort",
  "comi": "comic",
  "comm": "common",
  "comp": "company",
  "conc": "concert",
  "cond": "conduct",
  "conf": "confirm",
  "cong": "congress",
  "conn": "connect",
  "cons": "consider",
  "cont": "control",
  "conv": "convince",
  "cook": "cook",
  "cool": "cool",
  "copp": "copper",
  "copy": "copy",
  "cora": "coral",
  "core": "core",
  "corn": "corn",
  "corr": "correct",
  "cost": "cost",
  "cott": "cotton",
  "couc": "couch",
  "coun": "country",
  "coup": "couple",
  "cour": "course",
  "cous": "cousin",
  "cove": "cover",
  "coyo": "coyote",
  "crac": "crack",
  "crad": "cradle",
  "craf": "craft",
  "cram": "cram",
  "cran": "crane",
  "cras": "crash",
  "crat": "crater",
  "craw": "crawl",
  "craz": "crazy",
  "crea": "cream",
  "cred": "credit",
  "cree": "creek",
  "crew": "crew",
  "cric": "cricket",
  "crim": "crime",
  "cris": "crisp",
  "crit": "critic",
  "crop": "crop",
  "cros": "cross",
  "crou": "crouch",
  "crow": "crowd",
  "cruc": "crucial",
  "crue": "cruel",
  "crui": "cruise",
  "crum": "crumble",
  "crun": "crunch",
  "crus": "crush",
  "cry-": "cry",
  "crys": "crystal",
  "cube": "cube",
  "cult": "culture",
  "cup-": "cup",
  "cupb": "cupboard",
  "curi": "curious",
  "curr": "current",
  "curt": "curtain",
  "curv": "curve",
  "cush": "cushion",
  "cust": "custom",
  "cute": "cute",
  "cycl": "cycle",
  "dad-": "dad",
  "dama": "damage",
  "damp": "damp",
  "danc": "dance",
  "dang": "danger",
  "dari": "daring",
  "dash": "dash",
  "daug": "daughter",
  "dawn": "dawn",
  "day-": "day",
  "deal": "deal",
  "deba": "debate",
  "debr": "debris",
  "deca": "decade",
  "dece": "december",
  "deci": "decide",
  "decl": "decline",
  "deco": "decorate",
  "decr": "decrease",
  "deer": "deer",
  "defe": "defense",
  "defi": "define",
  "defy": "defy",
  "degr": "degree",
  "dela": "delay",
  "deli": "deliver",
  "dema": "demand",
  "demi": "demise",
  "deni": "denial",
  "dent": "dentist",
  "deny": "deny",
  "depa": "depart",
  "depe": "depend",
  "depo": "deposit",
  "dept": "depth",
  "depu": "deputy",
  "deri": "derive",
  "desc": "describe",
  "dese": "desert",
  "desi": "design",
  "desk": "desk",
  "desp": "despair",
  "dest": "destroy",
  "deta": "detail",
  "dete": "detect",
  "deve": "develop",
  "devi": "device",
  "devo": "devote",
  "diag": "diagram",
  "dial": "dial",
  "diam": "diamond",
  "diar": "diary",
  "dice": "dice",
  "dies": "diesel",
  "diet": "diet",
  "diff": "differ",
  "digi": "digital",
  "dign": "dignity",
  "dile": "dilemma",
  "dinn": "dinner",
  "dino": "dinosaur",
  "dire": "direct",
  "dirt": "dirt",
  "disa": "disagree",
  "disc": "discover",
  "dise": "disease",
  "dish": "dish",
  "dism": "dismiss",
  "diso": "disorder",
  "disp": "display",
  "dist": "distance",
  "dive": "divert",
  "divi": "divide",
  "divo": "divorce",
  "dizz": "dizzy",
  "doct": "doctor",
  "docu": "document",
  "dog-": "dog",
  "doll": "doll",
  "dolp": "dolphin",
  "doma": "domain",
  "dona": "donate",
  "donk": "donkey",
  "dono": "donor",
  "door": "door",
  "dose": "dose",
  "doub": "double",
  "dove": "dove",
  "draf": "draft",
  "drag": "dragon",
  "dram": "drama",
  "dras": "drastic",
  "draw": "draw",
  "drea": "dream",
  "dres": "dress",
  "drif": "drift",
  "dril": "drill",
  "drin": "drink",
  "drip": "drip",
  "driv": "drive",
  "drop": "drop",
  "drum": "drum",
  "dry-": "dry",
  "duck": "duck",
  "dumb": "dumb",
  "dune": "dune",
  "duri": "during",
  "dust": "dust",
  "dutc": "dutch",
  "duty": "duty",
  "dwar": "dwarf",
  "dyna": "dynamic",
  "eage": "eager",
  "eagl": "eagle",
  "earl": "early",
  "earn": "earn",
  "eart": "earth",
  "easi": "easily",
  "east": "east",
  "easy": "easy",
  "echo": "echo",
  "ecol": "ecology",
  "econ": "economy",
  "edge": "edge",
  "edit": "edit",
  "educ": "educate",
  "effo": "effort",
  "egg-": "egg",
  "eigh": "eight",
  "eith": "either",
  "elbo": "elbow",
  "elde": "elder",
  "elec": "electric",
  "eleg": "elegant",
  "elem": "element",
  "elep": "elephant",
  "elev": "elevator",
  "elit": "elite",
  "else": "else",
  "emba": "embark",
  "embo": "embody",
  "embr": "embrace",
  "emer": "emerge",
  "emot": "emotion",
  "empl": "employ",
  "empo": "empower",
  "empt": "empty",
  "enab": "enable",
  "enac": "enact",
  "end-": "end",
  "endl": "endless",
  "endo": "endorse",
  "enem": "enemy",
  "ener": "energy",
  "enfo": "enforce",
  "enga": "engage",
  "engi": "engine",
  "enha": "enhance",
  "enjo": "enjoy",
  "enli": "enlist",
  "enou": "enough",
  "enri": "enrich",
  "enro": "enroll",
  "ensu": "ensure",
  "ente": "enter",
  "enti": "entire",
  "entr": "entry",
  "enve": "envelope",
  "epis": "episode",
  "equa": "equal",
  "equi": "equip",
  "era-": "era",
  "eras": "erase",
  "erod": "erode",
  "eros": "erosion",
  "erro": "error",
  "erup": "erupt",
  "esca": "escape",
  "essa": "essay",
  "esse": "essence",
  "esta": "estate",
  "eter": "eternal",
  "ethi": "ethics",
  "evid": "evidence",
  "evil": "evil",
  "evok": "evoke",
  "evol": "evolve",
  "exac": "exact",
  "exam": "example",
  "exce": "excess",
  "exch": "exchange",
  "exci": "excite",
  "excl": "exclude",
  "excu": "excuse",
  "exec": "execute",
  "exer": "exercise",
  "exha": "exhaust",
  "exhi": "exhibit",
  "exil": "exile",
  "exis": "exist",
  "exit": "exit",
  "exot": "exotic",
  "expa": "expand",
  "expe": "expect",
  "expi": "expire",
  "expl": "explain",
  "expo": "expose",
  "expr": "express",
  "exte": "extend",
  "extr": "extra",
  "eye-": "eye",
  "eyeb": "eyebrow",
  "fabr": "fabric",
  "face": "face",
  "facu": "faculty",
  "fade": "fade",
  "fain": "faint",
  "fait": "faith",
  "fall": "fall",
  "fals": "false",
  "fame": "fame",
  "fami": "family",
  "famo": "famous",
  "fan-": "fan",
  "fanc": "fancy",
  "fant": "fantasy",
  "farm": "farm",
  "fash": "fashion",
  "fat-": "fat",
  "fata": "fatal",
  "fath": "father",
  "fati": "fatigue",
  "faul": "fault",
  "favo": "favorite",
  "feat": "feature",
  "febr": "february",
  "fede": "federal",
  "fee-": "fee",
  "feed": "feed",
  "feel": "feel",
  "fema": "female",
  "fenc": "fence",
  "fest": "festival",
  "fetc": "fetch",
  "feve": "fever",
  "few-": "few",
  "fibe": "fiber",
  "fict": "fiction",
  "fiel": "field",
  "figu": "figure",
  "file": "file",
  "film": "film",
  "filt": "filter",
  "fina": "final",
  "find": "find",
  "fine": "fine",
  "fing": "finger",
  "fini": "finish",
  "fire": "fire",
  "firm": "firm",
  "firs": "first",
  "fisc": "fiscal",
  "fish": "fish",
  "fit-": "fit",
  "fitn": "fitness",
  "fix-": "fix",
  "flag": "flag",
  "flam": "flame",
  "flas": "flash",
  "flat": "flat",
  "flav": "flavor",
  "flee": "flee",
  "flig": "flight",
  "flip": "flip",
  "floa": "float",
  "floc": "flock",
  "floo": "floor",
  "flow": "flower",
  "flui": "fluid",
  "flus": "flush",
  "fly-": "fly",
  "foam": "foam",
  "focu": "focus",
  "fog-": "fog",
  "foil": "foil",
  "fold": "fold",
  "foll": "follow",
  "food": "food",
  "foot": "foot",
  "forc": "force",
  "fore": "forest",
  "forg": "forget",
  "fork": "fork",
  "fort": "fortune",
  "foru": "forum",
  "forw": "forward",
  "foss": "fossil",
  "fost": "foster",
  "foun": "found",
  "fox-": "fox",
  "frag": "fragile",
  "fram": "frame",
  "freq": "frequent",
  "fres": "fresh",
  "frie": "friend",
  "frin": "fringe",
  "frog": "frog",
  "fron": "front",
  "fros": "frost",
  "frow": "frown",
  "froz": "frozen",
  "frui": "fruit",
  "fuel": "fuel",
  "fun-": "fun",
  "funn": "funny",
  "furn": "furnace",
  "fury": "fury",
  "futu": "future",
  "gadg": "gadget",
  "gain": "gain",
  "gala": "galaxy",
  "gall": "gallery",
  "game": "game",
  "gap-": "gap",
  "gara": "garage",
  "garb": "garbage",
  "gard": "garden",
  "garl": "garlic",
  "garm": "garment",
  "gas-": "gas",
  "gasp": "gasp",
  "gate": "gate",
  "gath": "gather",
  "gaug": "gauge",
  "gaze": "gaze",
  "gene": "general",
  "geni": "genius",
  "genr": "genre",
  "gent": "gentle",
  "genu": "genuine",
  "gest": "gesture",
  "ghos": "ghost",
  "gian": "giant",
  "gift": "gift",
  "gigg": "giggle",
  "ging": "ginger",
  "gira": "giraffe",
  "girl": "girl",
  "give": "give",
  "glad": "glad",
  "glan": "glance",
  "glar": "glare",
  "glas": "glass",
  "glid": "glide",
  "glim": "glimpse",
  "glob": "globe",
  "gloo": "gloom",
  "glor": "glory",
  "glov": "glove",
  "glow": "glow",
  "glue": "glue",
  "goat": "goat",
  "godd": "goddess",
  "gold": "gold",
  "good": "good",
  "goos": "goose",
  "gori": "gorilla",
  "gosp": "gospel",
  "goss": "gossip",
  "gove": "govern",
  "gown": "gown",
  "grab": "grab",
  "grac": "grace",
  "grai": "grain",
  "gran": "grant",
  "grap": "grape",
  "gras": "grass",
  "grav": "gravity",
  "grea": "great",
  "gree": "green",
  "grid": "grid",
  "grie": "grief",
  "grit": "grit",
  "groc": "grocery",
  "grou": "group",
  "grow": "grow",
  "grun": "grunt",
  "guar": "guard",
  "gues": "guess",
  "guid": "guide",
  "guil": "guilt",
  "guit": "guitar",
  "gun-": "gun",
  "gym-": "gym",
  "habi": "habit",
  "hair": "hair",
  "half": "half",
  "hamm": "hammer",
  "hams": "hamster",
  "hand": "hand",
  "happ": "happy",
  "harb": "harbor",
  "hard": "hard",
  "hars": "harsh",
  "harv": "harvest",
  "hat-": "hat",
  "have": "have",
  "hawk": "hawk",
  "haza": "hazard",
  "head": "head",
  "heal": "health",
  "hear": "heart",
  "heav": "heavy",
  "hedg": "hedgehog",
  "heig": "height",
  "hell": "hello",
  "helm": "helmet",
  "help": "help",
  "hen-": "hen",
  "hero": "hero",
  "hidd": "hidden",
  "high": "high",
  "hill": "hill",
  "hint": "hint",
  "hip-": "hip",
  "hire": "hire",
  "hist": "history",
  "hobb": "hobby",
  "hock": "hockey",
  "hold": "hold",
  "hole": "hole",
  "holi": "holiday",
  "holl": "hollow",
  "home": "home",
  "hone": "honey",
  "hood": "hood",
  "hope": "hope",
  "horn": "horn",
  "horr": "horror",
  "hors": "horse",
  "hosp": "hospital",
  "host": "host",
  "hote": "hotel",
  "hour": "hour",
  "hove": "hover",
  "hub-": "hub",
  "huge": "huge",
  "huma": "human",
  "humb": "humble",
  "humo": "humor",
  "hund": "hundred",
  "hung": "hungry",
  "hunt": "hunt",
  "hurd": "hurdle",
  "hurr": "hurry",
  "hurt": "hurt",
  "husb": "husband",
  "hybr": "hybrid",
  "ice-": "ice",
  "icon": "icon",
  "idea": "idea",
  "iden": "identify",
  "idle": "idle",
  "igno": "ignore",
  "ill-": "ill",
  "ille": "illegal",
  "illn": "illness",
  "imag": "image",
  "imit": "imitate",
  "imme": "immense",
  "immu": "immune",
  "impa": "impact",
  "impo": "impose",
  "impr": "improve",
  "impu": "impulse",
  "inch": "inch",
  "incl": "include",
  "inco": "income",
  "incr": "increase",
  "inde": "index",
  "indi": "indicate",
  "indo": "indoor",
  "indu": "industry",
  "infa": "infant",
  "infl": "inflict",
  "info": "inform",
  "inha": "inhale",
  "inhe": "inherit",
  "init": "initial",
  "inje": "inject",
  "inju": "injury",
  "inma": "inmate",
  "inne": "inner",
  "inno": "innocent",
  "inpu": "input",
  "inqu": "inquiry",
  "insa": "insane",
  "inse": "insect",
  "insi": "inside",
  "insp": "inspire",
  "inst": "install",
  "inta": "intact",
  "inte": "interest",
  "into": "into",
  "inve": "invest",
  "invi": "invite",
  "invo": "involve",
  "iron": "iron",
  "isla": "island",
  "isol": "isolate",
  "issu": "issue",
  "item": "item",
  "ivor": "ivory",
  "jack": "jacket",
  "jagu": "jaguar",
  "jar-": "jar",
  "jazz": "jazz",
  "jeal": "jealous",
  "jean": "jeans",
  "jell": "jelly",
  "jewe": "jewel",
  "job-": "job",
  "join": "join",
  "joke": "joke",
  "jour": "journey",
  "joy-": "joy",
  "judg": "judge",
  "juic": "juice",
  "jump": "jump",
  "jung": "jungle",
  "juni": "junior",
  "junk": "junk",
  "just": "just",
  "kang": "kangaroo",
  "keen": "keen",
  "keep": "keep",
  "ketc": "ketchup",
  "key-": "key",
  "kick": "kick",
  "kid-": "kid",
  "kidn": "kidney",
  "kind": "kind",
  "king": "kingdom",
  "kiss": "kiss",
  "kit-": "kit",
  "kitc": "kitchen",
  "kite": "kite",
  "kitt": "kitten",
  "kiwi": "kiwi",
  "knee": "knee",
  "knif": "knife",
  "knoc": "knock",
  "know": "know",
  "lab-": "lab",
  "labe": "label",
  "labo": "labor",
  "ladd": "ladder",
  "lady": "lady",
  "lake": "lake",
  "lamp": "lamp",
  "lang": "language",
  "lapt": "laptop",
  "larg": "large",
  "late": "later",
  "lati": "latin",
  "laug": "laugh",
  "laun": "laundry",
  "lava": "lava",
  "law-": "law",
  "lawn": "lawn",
  "laws": "lawsuit",
  "laye": "layer",
  "lazy": "lazy",
  "lead": "leader",
  "leaf": "leaf",
  "lear": "learn",
  "leav": "leave",
  "lect": "lecture",
  "left": "left",
  "leg-": "leg",
  "lega": "legal",
  "lege": "legend",
  "leis": "leisure",
  "lemo": "lemon",
  "lend": "lend",
  "leng": "length",
  "lens": "lens",
  "leop": "leopard",
  "less": "lesson",
  "lett": "letter",
  "leve": "level",
  "liar": "liar",
  "libe": "liberty",
  "libr": "library",
  "lice": "license",
  "life": "life",
  "lift": "lift",
  "ligh": "light",
  "like": "like",
  "limb": "limb",
  "limi": "limit",
  "link": "link",
  "lion": "lion",
  "liqu": "liquid",
  "list": "list",
  "litt": "little",
  "live": "live",
  "liza": "lizard",
  "load": "load",
  "loan": "loan",
  "lobs": "lobster",
  "loca": "local",
  "lock": "lock",
  "logi": "logic",
  "lone": "lonely",
  "long": "long",
  "loop": "loop",
  "lott": "lottery",
  "loud": "loud",
  "loun": "lounge",
  "love": "love",
  "loya": "loyal",
  "luck": "lucky",
  "lugg": "luggage",
  "lumb": "lumber",
  "luna": "lunar",
  "lunc": "lunch",
  "luxu": "luxury",
  "lyri": "lyrics",
  "mach": "machine",
  "mad-": "mad",
  "magi": "magic",
  "magn": "magnet",
  "maid": "maid",
  "mail": "mail",
  "main": "main",
  "majo": "major",
  "make": "make",
  "mamm": "mammal",
  "man-": "man",
  "mana": "manage",
  "mand": "mandate",
  "mang": "mango",
  "mans": "mansion",
  "manu": "manual",
  "mapl": "maple",
  "marb": "marble",
  "marc": "march",
  "marg": "margin",
  "mari": "marine",
  "mark": "market",
  "marr": "marriage",
  "mask": "mask",
  "mass": "mass",
  "mast": "master",
  "matc": "match",
  "mate": "material",
  "math": "math",
  "matr": "matrix",
  "matt": "matter",
  "maxi": "maximum",
  "maze": "maze",
  "mead": "meadow",
  "mean": "mean",
  "meas": "measure",
  "meat": "meat",
  "mech": "mechanic",
  "meda": "medal",
  "medi": "media",
  "melo": "melody",
  "melt": "melt",
  "memb": "member",
  "memo": "memory",
  "ment": "mention",
  "menu": "menu",
  "merc": "mercy",
  "merg": "merge",
  "meri": "merit",
  "merr": "merry",
  "mesh": "mesh",
  "mess": "message",
  "meta": "metal",
  "meth": "method",
  "midd": "middle",
  "midn": "midnight",
  "milk": "milk",
  "mill": "million",
  "mimi": "mimic",
  "mind": "mind",
  "mini": "minimum",
  "mino": "minor",
  "minu": "minute",
  "mira": "miracle",
  "mirr": "mirror",
  "mise": "misery",
  "miss": "miss",
  "mist": "mistake",
  "mix-": "mix",
  "mixe": "mixed",
  "mixt": "mixture",
  "mobi": "mobile",
  "mode": "model",
  "modi": "modify",
  "mom-": "mom",
  "mome": "moment",
  "moni": "monitor",
  "monk": "monkey",
  "mons": "monster",
  "mont": "month",
  "moon": "moon",
  "mora": "moral",
  "more": "more",
  "morn": "morning",
  "mosq": "mosquito",
  "moth": "mother",
  "moti": "motion",
  "moto": "motor",
  "moun": "mountain",
  "mous": "mouse",
  "move": "move",
  "movi": "movie",
  "much": "much",
  "muff": "muffin",
  "mule": "mule",
  "mult": "multiply",
  "musc": "muscle",
  "muse": "museum",
  "mush": "mushroom",
  "musi": "music",
  "must": "must",
  "mutu": "mutual",
  "myse": "myself",
  "myst": "mystery",
  "myth": "myth",
  "naiv": "naive",
  "name": "name",
  "napk": "napkin",
  "narr": "narrow",
  "nast": "nasty",
  "nati": "nation",
  "natu": "nature",
  "near": "near",
  "neck": "neck",
  "need": "need",
  "nega": "negative",
  "negl": "neglect",
  "neit": "neither",
  "neph": "nephew",
  "nerv": "nerve",
  "nest": "nest",
  "net-": "net",
  "netw": "network",
  "neut": "neutral",
  "neve": "never",
  "news": "news",
  "next": "next",
  "nice": "nice",
  "nigh": "night",
  "nobl": "noble",
  "nois": "noise",
  "nomi": "nominee",
  "nood": "noodle",
  "norm": "normal",
  "nort": "north",
  "nose": "nose",
  "nota": "notable",
  "note": "note",
  "noth": "nothing",
  "noti": "notice",
  "nove": "novel",
  "now-": "now",
  "nucl": "nuclear",
  "numb": "number",
  "nurs": "nurse",
  "nut-": "nut",
  "oak-": "oak",
  "obey": "obey",
  "obje": "object",
  "obli": "oblige",
  "obsc": "obscure",
  "obse": "observe",
  "obta": "obtain",
  "obvi": "obvious",
  "occu": "occur",
  "ocea": "ocean",
  "octo": "october",
  "odor": "odor",
  "off-": "off",
  "offe": "offer",
  "offi": "office",
  "ofte": "often",
  "oil-": "oil",
  "okay": "okay",
  "old-": "old",
  "oliv": "olive",
  "olym": "olympic",
  "omit": "omit",
  "once": "once",
  "one-": "one",
  "onio": "onion",
  "onli": "online",
  "only": "only",
  "open": "open",
  "oper": "opera",
  "opin": "opinion",
  "oppo": "oppose",
  "opti": "option",
  "oran": "orange",
  "orbi": "orbit",
  "orch": "orchard",
  "orde": "order",
  "ordi": "ordinary",
  "orga": "organ",
  "orie": "orient",
  "orig": "original",
  "orph": "orphan",
  "ostr": "ostrich",
  "othe": "other",
  "outd": "outdoor",
  "oute": "outer",
  "outp": "output",
  "outs": "outside",
  "oval": "oval",
  "oven": "oven",
  "over": "over",
  "own-": "own",
  "owne": "owner",
  "oxyg": "oxygen",
  "oyst": "oyster",
  "ozon": "ozone",
  "pact": "pact",
  "padd": "paddle",
  "page": "page",
  "pair": "pair",
  "pala": "palace",
  "palm": "palm",
  "pand": "panda",
  "pane": "panel",
  "pani": "panic",
  "pant": "panther",
  "pape": "paper",
  "para": "parade",
  "pare": "parent",
  "park": "park",
  "parr": "parrot",
  "part": "party",
  "pass": "pass",
  "patc": "patch",
  "path": "path",
  "pati": "patient",
  "patr": "patrol",
  "patt": "pattern",
  "paus": "pause",
  "pave": "pave",
  "paym": "payment",
  "peac": "peace",
  "pean": "peanut",
  "pear": "pear",
  "peas": "peasant",
  "peli": "pelican",
  "pen-": "pen",
  "pena": "penalty",
  "penc": "pencil",
  "peop": "people",
  "pepp": "pepper",
  "perf": "perfect",
  "perm": "permit",
  "pers": "person",
  "pet-": "pet",
  "phon": "phone",
  "phot": "photo",
  "phra": "phrase",
  "phys": "physical",
  "pian": "piano",
  "picn": "picnic",
  "pict": "picture",
  "piec": "piece",
  "pig-": "pig",
  "pige": "pigeon",
  "pill": "pill",
  "pilo": "pilot",
  "pink": "pink",
  "pion": "pioneer",
  "pipe": "pipe",
  "pist": "pistol",
  "pitc": "pitch",
  "pizz": "pizza",
  "plac": "place",
  "plan": "planet",
  "plas": "plastic",
  "plat": "plate",
  "play": "play",
  "plea": "please",
  "pled": "pledge",
  "pluc": "pluck",
  "plug": "plug",
  "plun": "plunge",
  "poem": "poem",
  "poet": "poet",
  "poin": "point",
  "pola": "polar",
  "pole": "pole",
  "poli": "police",
  "pond": "pond",
  "pony": "pony",
  "pool": "pool",
  "popu": "popular",
  "port": "portion",
  "posi": "position",
  "poss": "possible",
  "post": "post",
  "pota": "potato",
  "pott": "pottery",
  "pove": "poverty",
  "powd": "powder",
  "powe": "power",
  "prac": "practice",
  "prai": "praise",
  "pred": "predict",
  "pref": "prefer",
  "prep": "prepare",
  "pres": "present",
  "pret": "pretty",
  "prev": "prevent",
  "pric": "price",
  "prid": "pride",
  "prim": "primary",
  "prin": "print",
  "prio": "priority",
  "pris": "prison",
  "priv": "private",
  "priz": "prize",
  "prob": "problem",
  "proc": "process",
  "prod": "produce",
  "prof": "profit",
  "prog": "program",
  "proj": "project",
  "prom": "promote",
  "proo": "proof",
  "prop": "property",
  "pros": "prosper",
  "prot": "protect",
  "prou": "proud",
  "prov": "provide",
  "publ": "public",
  "pudd": "pudding",
  "pull": "pull",
  "pulp": "pulp",
  "puls": "pulse",
  "pump": "pumpkin",
  "punc": "punch",
  "pupi": "pupil",
  "pupp": "puppy",
  "purc": "purchase",
  "puri": "purity",
  "purp": "purpose",
  "purs": "purse",
  "push": "push",
  "put-": "put",
  "puzz": "puzzle",
  "pyra": "pyramid",
  "qual": "quality",
  "quan": "quantum",
  "quar": "quarter",
  "ques": "question",
  "quic": "quick",
  "quit": "quit",
  "quiz": "quiz",
  "quot": "quote",
  "rabb": "rabbit",
  "racc": "raccoon",
  "race": "race",
  "rack": "rack",
  "rada": "radar",
  "radi": "radio",
  "rail": "rail",
  "rain": "rain",
  "rais": "raise",
  "rall": "rally",
  "ramp": "ramp",
  "ranc": "ranch",
  "rand": "random",
  "rang": "range",
  "rapi": "rapid",
  "rare": "rare",
  "rate": "rate",
  "rath": "rather",
  "rave": "raven",
  "raw-": "raw",
  "razo": "razor",
  "read": "ready",
  "real": "real",
  "reas": "reason",
  "rebe": "rebel",
  "rebu": "rebuild",
  "reca": "recall",
  "rece": "receive",
  "reci": "recipe",
  "reco": "record",
  "recy": "recycle",
  "redu": "reduce",
  "refl": "reflect",
  "refo": "reform",
  "refu": "refuse",
  "regi": "region",
  "regr": "regret",
  "regu": "regular",
  "reje": "reject",
  "rela": "relax",
  "rele": "release",
  "reli": "relief",
  "rely": "rely",
  "rema": "remain",
  "reme": "remember",
  "remi": "remind",
  "remo": "remove",
  "rend": "render",
  "rene": "renew",
  "rent": "rent",
  "reop": "reopen",
  "repa": "repair",
  "repe": "repeat",
  "repl": "replace",
  "repo": "report",
  "requ": "require",
  "resc": "rescue",
  "rese": "resemble",
  "resi": "resist",
  "reso": "resource",
  "resp": "response",
  "resu": "result",
  "reti": "retire",
  "retr": "retreat",
  "retu": "return",
  "reun": "reunion",
  "reve": "reveal",
  "revi": "review",
  "rewa": "reward",
  "rhyt": "rhythm",
  "rib-": "rib",
  "ribb": "ribbon",
  "rice": "rice",
  "rich": "rich",
  "ride": "ride",
  "ridg": "ridge",
  "rifl": "rifle",
  "righ": "right",
  "rigi": "rigid",
  "ring": "ring",
  "riot": "riot",
  "ripp": "ripple",
  "risk": "risk",
  "ritu": "ritual",
  "riva": "rival",
  "rive": "river",
  "road": "road",
  "roas": "roast",
  "robo": "robot",
  "robu": "robust",
  "rock": "rocket",
  "roma": "romance",
  "roof": "roof",
  "rook": "rookie",
  "room": "room",
  "rose": "rose",
  "rota": "rotate",
  "roug": "rough",
  "roun": "round",
  "rout": "route",
  "roya": "royal",
  "rubb": "rubber",
  "rude": "rude",
  "rug-": "rug",
  "rule": "rule",
  "run-": "run",
  "runw": "runway",
  "rura": "rural",
  "sad-": "sad",
  "sadd": "saddle",
  "sadn": "sadness",
  "safe": "safe",
  "sail": "sail",
  "sala": "salad",
  "salm": "salmon",
  "salo": "salon",
  "salt": "salt",
  "salu": "salute",
  "same": "same",
  "samp": "sample",
  "sand": "sand",
  "sati": "satisfy",
  "sato": "satoshi",
  "sauc": "sauce",
  "saus": "sausage",
  "save": "save",
  "say-": "say",
  "scal": "scale",
  "scan": "scan",
  "scar": "scare",
  "scat": "scatter",
  "scen": "scene",
  "sche": "scheme",
  "scho": "school",
  "scie": "science",
  "scis": "scissors",
  "scor": "scorpion",
  "scou": "scout",
  "scra": "scrap",
  "scre": "screen",
  "scri": "script",
  "scru": "scrub",
  "sea-": "sea",
  "sear": "search",
  "seas": "season",
  "seat": "seat",
  "seco": "second",
  "secr": "secret",
  "sect": "section",
  "secu": "security",
  "seed": "seed",
  "seek": "seek",
  "segm": "segment",
  "sele": "select",
  "sell": "sell",
  "semi": "seminar",
  "seni": "senior",
  "sens": "sense",
  "sent": "sentence",
  "seri": "series",
  "serv": "service",
  "sess": "session",
  "sett": "settle",
  "setu": "setup",
  "seve": "seven",
  "shad": "shadow",
  "shaf": "shaft",
  "shal": "shallow",
  "shar": "share",
  "shed": "shed",
  "shel": "shell",
  "sher": "sheriff",
  "shie": "shield",
  "shif": "shift",
  "shin": "shine",
  "ship": "ship",
  "shiv": "shiver",
  "shoc": "shock",
  "shoe": "shoe",
  "shoo": "shoot",
  "shop": "shop",
  "shor": "short",
  "shou": "shoulder",
  "shov": "shove",
  "shri": "shrimp",
  "shru": "shrug",
  "shuf": "shuffle",
  "shy-": "shy",
  "sibl": "sibling",
  "sick": "sick",
  "side": "side",
  "sieg": "siege",
  "sigh": "sight",
  "sign": "sign",
  "sile": "silent",
  "silk": "silk",
  "sill": "silly",
  "silv": "silver",
  "simi": "similar",
  "simp": "simple",
  "sinc": "since",
  "sing": "sing",
  "sire": "siren",
  "sist": "sister",
  "situ": "situate",
  "six-": "six",
  "size": "size",
  "skat": "skate",
  "sket": "sketch",
  "ski-": "ski",
  "skil": "skill",
  "skin": "skin",
  "skir": "skirt",
  "skul": "skull",
  "slab": "slab",
  "slam": "slam",
  "slee": "sleep",
  "slen": "slender",
  "slic": "slice",
  "slid": "slide",
  "slig": "slight",
  "slim": "slim",
  "slog": "slogan",
  "slot": "slot",
  "slow": "slow",
  "slus": "slush",
  "smal": "small",
  "smar": "smart",
  "smil": "smile",
  "smok": "smoke",
  "smoo": "smooth",
  "snac": "snack",
  "snak": "snake",
  "snap": "snap",
  "snif": "sniff",
  "snow": "snow",
  "soap": "soap",
  "socc": "soccer",
  "soci": "social",
  "sock": "sock",
  "soda": "soda",
  "soft": "soft",
  "sola": "solar",
  "sold": "soldier",
  "soli": "solid",
  "solu": "solution",
  "solv": "solve",
  "some": "someone",
  "song": "song",
  "soon": "soon",
  "sorr": "sorry",
  "sort": "sort",
  "soul": "soul",
  "soun": "sound",
  "soup": "soup",
  "sour": "source",
  "sout": "south",
  "spac": "space",
  "spar": "spare",
  "spat": "spatial",
  "spaw": "spawn",
  "spea": "speak",
  "spec": "special",
  "spee": "speed",
  "spel": "spell",
  "spen": "spend",
  "sphe": "sphere",
  "spic": "spice",
  "spid": "spider",
  "spik": "spike",
  "spin": "spin",
  "spir": "spirit",
  "spli": "split",
  "spoi": "spoil",
  "spon": "sponsor",
  "spoo": "spoon",
  "spor": "sport",
  "spot": "spot",
  "spra": "spray",
  "spre": "spread",
  "spri": "spring",
  "spy-": "spy",
  "squa": "square",
  "sque": "squeeze",
  "squi": "squirrel",
  "stab": "stable",
  "stad": "stadium",
  "staf": "staff",
  "stag": "stage",
  "stai": "stairs",
  "stam": "stamp",
  "stan": "stand",
  "star": "start",
  "stat": "state",
  "stay": "stay",
  "stea": "steak",
  "stee": "steel",
  "stem": "stem",
  "step": "step",
  "ster": "stereo",
  "stic": "stick",
  "stil": "still",
  "stin": "sting",
  "stoc": "stock",
  "stom": "stomach",
  "ston": "stone",
  "stoo": "stool",
  "stor": "story",
  "stov": "stove",
  "stra": "strategy",
  "stre": "street",
  "stri": "strike",
  "stro": "strong",
  "stru": "struggle",
  "stud": "student",
  "stuf": "stuff",
  "stum": "stumble",
  "styl": "style",
  "subj": "subject",
  "subm": "submit",
  "subw": "subway",
  "succ": "success",
  "such": "such",
  "sudd": "sudden",
  "suff": "suffer",
  "suga": "sugar",
  "sugg": "suggest",
  "suit": "suit",
  "summ": "summer",
  "sun-": "sun",
  "sunn": "sunny",
  "suns": "sunset",
  "supe": "super",
  "supp": "supply",
  "supr": "supreme",
  "sure": "sure",
  "surf": "surface",
  "surg": "surge",
  "surp": "surprise",
  "surr": "surround",
  "surv": "survey",
  "susp": "suspect",
  "sust": "sustain",
  "swal": "swallow",
  "swam": "swamp",
  "swap": "swap",
  "swar": "swarm",
  "swea": "swear",
  "swee": "sweet",
  "swif": "swift",
  "swim": "swim",
  "swin": "swing",
  "swit": "switch",
  "swor": "sword",
  "symb": "symbol",
  "symp": "symptom",
  "syru": "syrup",
  "syst": "system",
  "tabl": "table",
  "tack": "tackle",
  "tag-": "tag",
  "tail": "tail",
  "tale": "talent",
  "talk": "talk",
  "tank": "tank",
  "tape": "tape",
  "targ": "target",
  "task": "task",
  "tast": "taste",
  "tatt": "tattoo",
  "taxi": "taxi",
  "teac": "teach",
  "team": "team",
  "tell": "tell",
  "ten-": "ten",
  "tena": "tenant",
  "tenn": "tennis",
  "tent": "tent",
  "term": "term",
  "test": "test",
  "text": "text",
  "than": "thank",
  "that": "that",
  "them": "theme",
  "then": "then",
  "theo": "theory",
  "ther": "there",
  "they": "they",
  "thin": "thing",
  "this": "this",
  "thou": "thought",
  "thre": "three",
  "thri": "thrive",
  "thro": "throw",
  "thum": "thumb",
  "thun": "thunder",
  "tick": "ticket",
  "tide": "tide",
  "tige": "tiger",
  "tilt": "tilt",
  "timb": "timber",
  "time": "time",
  "tiny": "tiny",
  "tip-": "tip",
  "tire": "tired",
  "tiss": "tissue",
  "titl": "title",
  "toas": "toast",
  "toba": "tobacco",
  "toda": "today",
  "todd": "toddler",
  "toe-": "toe",
  "toge": "together",
  "toil": "toilet",
  "toke": "token",
  "toma": "tomato",
  "tomo": "tomorrow",
  "tone": "tone",
  "tong": "tongue",
  "toni": "tonight",
  "tool": "tool",
  "toot": "tooth",
  "top-": "top",
  "topi": "topic",
  "topp": "topple",
  "torc": "torch",
  "torn": "tornado",
  "tort": "tortoise",
  "toss": "toss",
  "tota": "total",
  "tour": "tourist",
  "towa": "toward",
  "towe": "tower",
  "town": "town",
  "toy-": "toy",
  "trac": "track",
  "trad": "trade",
  "traf": "traffic",
  "trag": "tragic",
  "trai": "train",
  "tran": "transfer",
  "trap": "trap",
  "tras": "trash",
  "trav": "travel",
  "tray": "tray",
  "trea": "treat",
  "tree": "tree",
  "tren": "trend",
  "tria": "trial",
  "trib": "tribe",
  "tric": "trick",
  "trig": "trigger",
  "trim": "trim",
  "trip": "trip",
  "trop": "trophy",
  "trou": "trouble",
  "truc": "truck",
  "true": "true",
  "trul": "truly",
  "trum": "trumpet",
  "trus": "trust",
  "trut": "truth",
  "try-": "try",
  "tube": "tube",
  "tuit": "tuition",
  "tumb": "tumble",
  "tuna": "tuna",
  "tunn": "tunnel",
  "turk": "turkey",
  "turn": "turn",
  "turt": "turtle",
  "twel": "twelve",
  "twen": "twenty",
  "twic": "twice",
  "twin": "twin",
  "twis": "twist",
  "two-": "two",
  "type": "type",
  "typi": "typical",
  "ugly": "ugly",
  "umbr": "umbrella",
  "unab": "unable",
  "unaw": "unaware",
  "uncl": "uncle",
  "unco": "uncover",
  "unde": "under",
  "undo": "undo",
  "unfa": "unfair",
  "unfo": "unfold",
  "unha": "unhappy",
  "unif": "uniform",
  "uniq": "unique",
  "unit": "unit",
  "univ": "universe",
  "unkn": "unknown",
  "unlo": "unlock",
  "unti": "until",
  "unus": "unusual",
  "unve": "unveil",
  "upda": "update",
  "upgr": "upgrade",
  "upho": "uphold",
  "upon": "upon",
  "uppe": "upper",
  "upse": "upset",
  "urba": "urban",
  "urge": "urge",
  "usag": "usage",
  "use-": "use",
  "used": "used",
  "usef": "useful",
  "usel": "useless",
  "usua": "usual",
  "util": "utility",
  "vaca": "vacant",
  "vacu": "vacuum",
  "vagu": "vague",
  "vali": "valid",
  "vall": "valley",
  "valv": "valve",
  "van-": "van",
  "vani": "vanish",
  "vapo": "vapor",
  "vari": "various",
  "vast": "vast",
  "vaul": "vault",
  "vehi": "vehicle",
  "velv": "velvet",
  "vend": "vendor",
  "vent": "venture",
  "venu": "venue",
  "verb": "verb",
  "veri": "verify",
  "vers": "version",
  "very": "very",
  "vess": "vessel",
  "vete": "veteran",
  "viab": "viable",
  "vibr": "vibrant",
  "vici": "vicious",
  "vict": "victory",
  "vide": "video",
  "view": "view",
  "vill": "village",
  "vint": "vintage",
  "viol": "violin",
  "virt": "virtual",
  "viru": "virus",
  "visa": "visa",
  "visi": "visit",
  "visu": "visual",
  "vita": "vital",
  "vivi": "vivid",
  "voca": "vocal",
  "voic": "voice",
  "void": "void",
  "volc": "volcano",
  "volu": "volume",
  "vote": "vote",
  "voya": "voyage",
  "wage": "wage",
  "wago": "wagon",
  "wait": "wait",
  "walk": "walk",
  "wall": "wall",
  "waln": "walnut",
  "want": "want",
  "warf": "warfare",
  "warm": "warm",
  "warr": "warrior",
  "wash": "wash",
  "wasp": "wasp",
  "wast": "waste",
  "wate": "water",
  "wave": "wave",
  "way-": "way",
  "weal": "wealth",
  "weap": "weapon",
  "wear": "wear",
  "weas": "weasel",
  "weat": "weather",
  "web-": "web",
  "wedd": "wedding",
  "week": "weekend",
  "weir": "weird",
  "welc": "welcome",
  "west": "west",
  "wet-": "wet",
  "whal": "whale",
  "what": "what",
  "whea": "wheat",
  "whee": "wheel",
  "when": "when",
  "wher": "where",
  "whip": "whip",
  "whis": "whisper",
  "wide": "wide",
  "widt": "width",
  "wife": "wife",
  "wild": "wild",
  "will": "will",
  "win-": "win",
  "wind": "window",
  "wine": "wine",
  "wing": "wing",
  "wink": "wink",
  "winn": "winner",
  "wint": "winter",
  "wire": "wire",
  "wisd": "wisdom",
  "wise": "wise",
  "wish": "wish",
  "witn": "witness",
  "wolf": "wolf",
  "woma": "woman",
  "wond": "wonder",
  "wood": "wood",
  "wool": "wool",
  "word": "word",
  "work": "work",
  "worl": "world",
  "worr": "worry",
  "wort": "worth",
  "wrap": "wrap",
  "wrec": "wreck",
  "wres": "wrestle",
  "wris": "wrist",
  "writ": "write",
  "wron": "wrong",
  "yard": "yard",
  "year": "year",
  "yell": "yellow",
  "you-": "you",
  "youn": "young",
  "yout": "youth",
  "zebr": "zebra",
  "zero": "zero",
  "zone": "zone",
  "zoo-": "zoo",
}
